temp-mail-so/__init__.py
temp-mail-so/temp_mail_so.py
temp_mail_so/__init__.py
temp_mail_so/temp_mail_so.py
temp_mail_so-1.0.2.dist-info/LICENSE
temp_mail_so-1.0.2.dist-info/METADATA
temp_mail_so-1.0.2.dist-info/WHEEL
temp_mail_so-1.0.2.dist-info/top_level.txt
temp_mail_so-1.0.2.dist-info/RECORD
