Metadata-Version: 2.1
Name: temp-mail-so
Version: 1.0.2
Summary: A Python SDK for TempMail.so temporary email service
Home-page: https://tempmail.so
Author: TempMail.so
Author-email: service@tempmail.so
License: UNKNOWN
Platform: UNKNOWN
Classifier: Programming Language :: Python :: 3
Classifier: License :: OSI Approved :: MIT License
Classifier: Operating System :: OS Independent
Requires-Python: >=3.6
License-File: LICENSE
Requires-Dist: requests (>=2.25.1)
